arcade_luma_api/__init__.py
arcade_luma_api/moar/Luma.json
arcade_luma_api/moar/openapi.json
arcade_luma_api/tools/__init__.py
arcade_luma_api/tools/request_body_schemas.py
arcade_luma_api/wrapper_tools/AddEventGuests.json
arcade_luma_api/wrapper_tools/AddEventHost.json
arcade_luma_api/wrapper_tools/AddEventToLumaCalendar.json
arcade_luma_api/wrapper_tools/AddUserToMembershipTier.json
arcade_luma_api/wrapper_tools/ApplyTagToCalendarMembers.json
arcade_luma_api/wrapper_tools/CheckEventExistence.json
arcade_luma_api/wrapper_tools/CreateEvent.json
arcade_luma_api/wrapper_tools/CreateEventCoupon.json
arcade_luma_api/wrapper_tools/CreateEventTicketType.json
arcade_luma_api/wrapper_tools/CreatePersonTag.json
arcade_luma_api/wrapper_tools/DeletePersonTag.json
arcade_luma_api/wrapper_tools/GenerateEventCoupon.json
arcade_luma_api/wrapper_tools/GenerateUploadUrl.json
arcade_luma_api/wrapper_tools/GetEventAdminInfo.json
arcade_luma_api/wrapper_tools/GetEventGuest.json
arcade_luma_api/wrapper_tools/GetEventGuests.json
arcade_luma_api/wrapper_tools/GetTicketTypeById.json
arcade_luma_api/wrapper_tools/GetUserInfo.json
arcade_luma_api/wrapper_tools/ImportPeopleToCalendar.json
arcade_luma_api/wrapper_tools/ListCalendarCoupons.json
arcade_luma_api/wrapper_tools/ListEventCoupons.json
arcade_luma_api/wrapper_tools/ListEventTicketTypes.json
arcade_luma_api/wrapper_tools/ListLumaCalendarEvents.json
arcade_luma_api/wrapper_tools/ListMembershipTiers.json
arcade_luma_api/wrapper_tools/ListPeople.json
arcade_luma_api/wrapper_tools/ListPersonTags.json
arcade_luma_api/wrapper_tools/LumaEntityLookup.json
arcade_luma_api/wrapper_tools/ModifyCoupon.json
arcade_luma_api/wrapper_tools/RemoveTagFromCalendarMembers.json
arcade_luma_api/wrapper_tools/SendGuestEventInvite.json
arcade_luma_api/wrapper_tools/SoftDeleteTicketType.json
arcade_luma_api/wrapper_tools/UpdateCoupon.json
arcade_luma_api/wrapper_tools/UpdateEvent.json
arcade_luma_api/wrapper_tools/UpdateGuestStatus.json
arcade_luma_api-1.0.0.dist-info/METADATA
arcade_luma_api-1.0.0.dist-info/WHEEL
arcade_luma_api-1.0.0.dist-info/entry_points.txt
arcade_luma_api-1.0.0.dist-info/licenses/LICENSE
arcade_luma_api-1.0.0.dist-info/RECORD
